{
  "date": "2026-06-03",
  "prev_date": "2026-06-02",
  "trends": {
    "西方奇幻": {
      "new_count": 3,
      "dropped_count": 3,
      "new_books": [
        "骑士不出恶语，只出暴击",
        "嫌我没用？我走后圣女黑化了",
        "西幻领主：每人每天给我一枚银币"
      ],
      "dropped_books": [
        {
          "title": "永夜求生：我在领地种出灾厄巨龙",
          "intro": "（评分刚出有点低，后面会涨）西幻领主+诡异求生+种田经营+培育巨龙+收获爽文 永夜降临，诡异横行，没有领地之火的庇护，万物皆亡！ 身为黄金麦穗侯爵家长子的雷格，父亲身亡，惨遭陷害， 被新国王与亲叔叔联"
        },
        {
          "title": "转生蒙眼修女的我，真不是深渊种",
          "intro": "【变身（不嫁）+偏轻百+西幻+剑与魔法+冒险+吞噬+精灵+兽耳娘】 （介意主角来亲戚的误入） 赵爽因填写一份问卷而穿越到类似中世纪欧洲的世界，刚睁眼就要面临一群……糕点（教廷）的围攻？ 小小糕点还反了"
        },
        {
          "title": "我在求生世界宴请诸神",
          "intro": "【法师】【群像】【天赋】 （次元法师团参上） 全民穿越，诸天求生。 李维的天赋是：宴请。 每日开启一场宴会，邀请自愿参与的友人，在宴会上分享自己的美食、装备、技能，获取巨量自由经验反馈。 …… 我们是"
        }
      ],
      "top_risers": [
        {
          "title": "小姐可以不要只对剑在意吗",
          "change": "+8"
        },
        {
          "title": "MC玩家的巫师之旅",
          "change": "+4"
        },
        {
          "title": "变身亡国龙娘？我是公主不是老婆",
          "change": "+2"
        }
      ],
      "top_fallers": [
        {
          "title": "转生贵族：从认萝莉妈妈开始",
          "change": "-2"
        },
        {
          "title": "性转魔女，不想被圣女抓住",
          "change": "-2"
        },
        {
          "title": "金龙领主：在贵族世界的放纵生活",
          "change": "-1"
        }
      ],
      "reads_growth": [
        {
          "title": "小姐可以不要只对剑在意吗",
          "growth": "+8000"
        },
        {
          "title": "被放逐的勇者，和魔族公主私奔了",
          "growth": "+7000"
        },
        {
          "title": "领主，精灵虫，巨龙",
          "growth": "+6000"
        }
      ],
      "summary": "**🔥 题材趋势** 榜单呈现明显的“变身/性转”热潮（TOP20中占据6席）和“多女主/后宫”倾向。系统、领主种田、黑深残开局（如黑兽、放逐勇者）仍是主流设定。\n**📖 读者偏好** 读者偏爱高爽点、快节奏的“杀伐果断”或“吃糖”日常。简介中突出“无女主”或“多女主”的极端标签，以及“强制爱”“调教”等强冲突元素的作品更容易吸引眼球。\n**🆕 新上榜作品** 新上榜的《骑士不出恶语》和《嫌我没用？我走后圣女黑化了》均属非典型西幻，前者结合网游+数据无敌，后者主打“工业革命+逆袭”，显示读者对套路的微创新需求。\n**📉 掉出榜单** 掉榜作品《永夜求生》和《转生蒙眼修女》均为混合题材，说明在竞争激烈的榜单中，纯粹的“西幻领主+诡异求生”或“修女变百”路线热度难以持续。\n**💡 值得关注** 《被骗当女仆，我怎么成血族公主了》以“反面角色趁热捡尸”的反套路开局脱颖而出，在读数稳固，其“养成+虐恋”的CP模式在“变百”赛道中展现了独特竞争力。"
    },
    "东方仙侠": {
      "new_count": 2,
      "dropped_count": 2,
      "new_books": [
        "同学们选武侠仙侠，我选洪荒世界",
        "洪荒：人族泣血，求老祖救我族人"
      ],
      "dropped_books": [
        {
          "title": "西游：大师兄住手，那是我兄弟！",
          "intro": "本书又名：李世民：怎么派了个取经的，灵山都来朝贡了！ “大师兄别动手！这妖怪是我拜把子兄弟！” 一句话，让举着金箍棒的孙悟空当场僵住，让一心求经的唐僧彻底麻了。 陵游，万年前穿入西游，没修逆天神功，没"
        },
        {
          "title": "洪荒：国术入道，开局拜师元始",
          "intro": "洪荒黑暗时代，人族孱弱，被妖族视为血食，被巫族奴役，命如草芥。 现代国术爱好者王斌穿越成青石部落少年，以血肉之躯在夹缝中杀出一条通天大道！ 万里独行，餐风饮露，他以凡人之躯硬生生攀上昆仑绝顶。 元始天"
        }
      ],
      "top_risers": [
        {
          "title": "修仙：今天又是被妖女破功的一天",
          "change": "+3"
        },
        {
          "title": "西游：苟在猴哥体内满天神佛慌了",
          "change": "+2"
        },
        {
          "title": "家族：从契约白蛇开始伪装天才",
          "change": "+2"
        }
      ],
      "top_fallers": [
        {
          "title": "洪荒：摇钱聚宝，八方来财！",
          "change": "-4"
        },
        {
          "title": "仙族：暮年金丹，命格大器晚成！",
          "change": "-3"
        },
        {
          "title": "冥河的道德绑架大阵",
          "change": "-3"
        }
      ],
      "reads_growth": [
        {
          "title": "西游：苟在猴哥体内满天神佛慌了",
          "growth": "+4.7万"
        },
        {
          "title": "家族：从契约白蛇开始伪装天才",
          "growth": "+8000"
        },
        {
          "title": "洪荒对比：开局混元无极金仙太清",
          "growth": "+7000"
        }
      ],
      "summary": "**🔥 题材趋势** 榜单高度集中于“洪荒”与“西游”两大经典IP的改编。洪荒流以“重构神话”（如造物主、拒绝夺舍）为主流；西游流则热衷于“改变剧情”（如拯救猴哥、玉帝秘书）。\n**📖 读者偏好** 读者偏好两极：一极是追求极致爽感的“无敌流”和“杀伐果断”（帝庭之主、天道求我）；另一极是偏好“日常幽默”和“反套路”（采药捡到剑仙、妖女破功）。榜单前三名霸榜，显示强大头部效应。\n**🆕 新上榜作品** 新上榜的《同学们选武侠仙侠，我选洪荒世界》利用了“信息差”爽点（蓝星人懂洪荒），《人族泣血》则是典型的“受辱-爆发”情绪流，均精准切中市场。\n**📉 掉出榜单** 掉榜作品《西游：大师兄住手》和《洪荒：国术入道》说明，在头部作品挤压下，单纯的“兄弟情”设定和“黑暗洪荒+国术”的结合点热度不足。\n**💡 值得关注** 值得注意的是，《西游：苟在猴哥体内满天神佛慌了》排名跃升至第二，其“养成孙悟空的幕后老爷爷”设定具有极强的创新性，成功在传统西游框架下开辟了“稳健腹黑”的新叙事。"
    },
    "科幻末世": {
      "new_count": 2,
      "dropped_count": 2,
      "new_books": [
        "在下班中王，末世最猖狂",
        "无限末世：美妇求带竟是仇敌至亲"
      ],
      "dropped_books": [
        {
          "title": "班级求生：被赶下车后，成团宠了",
          "intro": "【全民】【房车】【多】【团宠】【异能】【公路求生】 一场全民房车公路求生穿越开启。 江野跟班级里的女生分配到了同一个房车上。 “穿越了，没想到真的穿越了。” “咦！这里怎么还有男人？” “集美们！不就"
        },
        {
          "title": "小区求生：我能看见隐藏进化链",
          "intro": "新书刚出评分，持续上涨中！ 【小区穿越+灵兽世界漂流+御兽进化+基地建设+黑雾求生】 一夜之间，锦和家园整座小区被扔进异界谷地。 手机断网，黑雾倒计时开启，楼外灵兽游荡，楼内人心先乱。 而黑雾侵袭只是"
        }
      ],
      "top_risers": [
        {
          "title": "全民开荒求生：开局挖出强运词条",
          "change": "+5"
        },
        {
          "title": "天序007：化龙",
          "change": "+4"
        },
        {
          "title": "木筏求生，开局捡到大蜜蜜",
          "change": "+4"
        }
      ],
      "top_fallers": [
        {
          "title": "末日氦闪：我用飞船装走整个华夏",
          "change": "-6"
        },
        {
          "title": "一人：丧尸做耗材，我炼僵成圣",
          "change": "-4"
        },
        {
          "title": "公路求生：我开直升机杀穿末日",
          "change": "-4"
        }
      ],
      "reads_growth": [
        {
          "title": "死亡列车：开局SSS级天赋！",
          "growth": "+2.4万"
        },
        {
          "title": "天序007：化龙",
          "growth": "+2.1万"
        },
        {
          "title": "全民开荒求生：开局挖出强运词条",
          "growth": "+1.0万"
        }
      ],
      "summary": "**🔥 题材趋势**  \n“求生+开局金手指”仍是核心，高频元素包括重生、系统、种田、上交国家、多女主/无CP。扎堆设定为“开局抽到SSS天赋/强运词条”与“末世+公路/木筏/小区求生”，同质化明显。\n\n**📖 读者偏好**  \n读者偏好“爽”向、杀伐果断、金手指强度拉满（SSS级天赋/唯一天赋），不圣母+快速升级是刚需；系统类、重生预知类最稳。\n\n**🆕 新上榜作品**  \n- 《在下班中王，末世最猖狂》：“班中王”人设+每日情报系统，校园反套路末世流，差异化在“学生领袖”设定。  \n- 《无限末世：美妇求带竟是仇敌至亲》：多女+伦理冲突标签，靠极致情绪钩子吸引点击。\n\n**📉 掉出榜单**  \n- 《班级求生：被赶下车后，成团宠了》（公路求生+团宠），题材过饱和，缺乏新意。  \n- 《小区求生：我能看见隐藏进化链》（小区穿越+御兽进化），设定与头部作品重叠，竞争力不足。\n\n**💡 值得关注**  \n- 《开局穿越土卫六，人类就在我隔壁》：星际种田+非上交流，无CP差异化明显，13万在读领跑。  \n- 《天序007：化龙》：龙系觉醒+灰雾末世，都市异变题材新颖，排名上升势头强。"
    },
    "都市日常": {
      "new_count": 0,
      "dropped_count": 0,
      "new_books": [],
      "dropped_books": [],
      "top_risers": [
        {
          "title": "让你带娃，你带出个魔丸！",
          "change": "+4"
        },
        {
          "title": "要离婚了才发现我有二十亿比特币",
          "change": "+3"
        },
        {
          "title": "穿越后我光速切割关系，但她不让",
          "change": "+2"
        }
      ],
      "top_fallers": [
        {
          "title": "女尊：他逐渐沉沦",
          "change": "-4"
        },
        {
          "title": "压抑大小姐每天都想被亲哭！",
          "change": "-3"
        },
        {
          "title": "女局长：扫黑风暴",
          "change": "-2"
        }
      ],
      "reads_growth": [
        {
          "title": "要离婚了才发现我有二十亿比特币",
          "growth": "+4.6万"
        },
        {
          "title": "穿越后我光速切割关系，但她不让",
          "growth": "+2.4万"
        },
        {
          "title": "黑道风云之乔四军师小克王伟范",
          "growth": "+1.6万"
        }
      ],
      "summary": "**🔥 题材趋势** “病娇”与“追夫火葬场”仍是核心流量密码，类型融合加剧，与“带娃”、“重生”、“失忆”等元素高频结合。女尊、乡村等细分题材也占有一席之地，内容多样化趋势明显。\n**📖 读者偏好** 用户偏爱强烈的情感冲突与身份反转，如离婚、失忆、情敌回归等戏剧性开场。高在读作品普遍具备强戏剧张力和密集的爽点/虐点，对“男主清醒”、“女追男”设定接受度高。\n**🆕 新上榜作品** 无新上榜作品，头部格局稳定。\n**📉 掉出榜单** 无作品掉出榜单。\n**💡 值得关注** 《让你带娃，你带出个魔丸！》排名大幅上升，显示出“萌娃”+“反差”组合的强大潜力，值得赛道创作者深入研究其爽点设计。"
    },
    "都市修真": {
      "new_count": 2,
      "dropped_count": 2,
      "new_books": [
        "刘天仙成婚，老公居然是长生者？",
        "综漫世界的快乐修仙日常"
      ],
      "dropped_books": [
        {
          "title": "傻大壮，乡野好快活",
          "intro": "【乡村+神医+爽文+热血+无敌+美女】幸福村有个傻子叫王大壮，为保护嫂子被村中恶霸撞破脑袋后机缘巧合下获得了仙人传承，从此逆天改命，一手银针掌生死，仙人指路专治各种不服，最终富可敌国，走向人生巅峰!"
        },
        {
          "title": "都市：100天成仙，杀穿全球",
          "intro": "【杀伐果断➕无敌➕单女主➕有女儿不喜勿入】 被污蔑开除、甲方让叫爸爸、女总裁的眼神像看垃圾、父亲重病等待钱，甲方转账0.01践踏尊严。 林奇觉醒前世道果封印，境界每天解封一层。 杀，杀穿一切不公，杀到"
        }
      ],
      "top_risers": [
        {
          "title": "词条加一天升一境，上大学就成仙",
          "change": "+4"
        },
        {
          "title": "力量每天翻倍，女帝女儿被吓懵了",
          "change": "+3"
        },
        {
          "title": "收留返现：从暴击精神小妹开始！",
          "change": "+2"
        }
      ],
      "top_fallers": [
        {
          "title": "仙人，你怎么从镜子里出来了！",
          "change": "-4"
        },
        {
          "title": "乡村女人找老公",
          "change": "-1"
        }
      ],
      "reads_growth": [
        {
          "title": "入夜，征服",
          "growth": "+8.7万"
        },
        {
          "title": "开局相亲女警察，获得降龙十八掌",
          "growth": "+1.9万"
        },
        {
          "title": "收留返现：从暴击精神小妹开始！",
          "growth": "+1.8万"
        }
      ],
      "summary": "**🔥 题材趋势** “古今碰撞”是绝对主线，如《先秦炼气两千年》与《骗子道士》。同时，“系统收留”、“词条升级”等轻量化、游戏化的修仙设定热度极高，与传统修仙叙事并行。\n**📖 读者偏好** 读者追求高代入感与“降维打击”的爽感，偏好主角拥有独特但强大的金手指（如系统、传承）。对“废柴逆袭”、“隐居大佬”、“美强惨”等设定有稳定需求，同时“轻松幽默”元素更易出圈。\n**🆕 新上榜作品** 《刘天仙成婚，老公居然是长生者？》以“明星婚恋+长生者”的跨界组合切入，制造强烈反差；《综漫世界的快乐修仙日常》则尝试与二次元文化融合，探索新受众。\n**📉 掉出榜单** 《傻大壮，乡野好快活》与《都市：100天成仙，杀穿全球》掉出榜单，表明纯粹的“乡村修仙”和“极速成仙”套路热度有所回落。\n**💡 值得关注** 《词条加一天升一境，上大学就成仙》排名快速上升，其“系统流+校园”的轻小说式写法，精准捕获了年轻读者对低门槛、高频爽点修仙的偏好。"
    },
    "都市高武": {
      "new_count": 2,
      "dropped_count": 2,
      "new_books": [
        "国运求生：我一只鬼被选进去了！",
        "我瞎编的禁忌序列，国家当真了"
      ],
      "dropped_books": [
        {
          "title": "穿越异世界：我成为了超人",
          "intro": "【超人能力+杀伐果断+无敌+肉体碾压+赛博朋克+都市异能】 陈烬本来是探测队的一员，偶然间在一次探测活动中，意外穿越到了异世界。 这个世界充满奇幻，但也同样充满危机。 在这里，科技与异能并存，联邦与帝"
        },
        {
          "title": "一群机制怪里，出了个劲大的",
          "intro": "（评分刚出会偏低，后面会涨的） 在一堆机制怪里出了个劲大的，那你得考虑考虑，他的劲有多大了。 你以为的现代都市，只有车水马龙？ 殊不知一件件超自然事件皆被超凡世界掩盖着，普通人一生都难窥探真相。 大四"
        }
      ],
      "top_risers": [
        {
          "title": "重生泰坦烛龙，人类你们慌什么？",
          "change": "+1"
        },
        {
          "title": "开局徒手抬钢卷，我的天赋叫劲大",
          "change": "+1"
        },
        {
          "title": "濒死触发二阶段？我先捅自己一刀",
          "change": "+1"
        }
      ],
      "top_fallers": [
        {
          "title": "开局禁区兽皇，捡了个女帝当女儿",
          "change": "-1"
        },
        {
          "title": "玩个游戏，你们非说我在收容异常",
          "change": "-1"
        },
        {
          "title": "国运擂台：开局替换粉底液将军！",
          "change": "-1"
        }
      ],
      "reads_growth": [
        {
          "title": "嘉豪就变强？操场雨中舞剑开天门",
          "growth": "+19.3万"
        },
        {
          "title": "重生泰坦烛龙，人类你们慌什么？",
          "growth": "+6.9万"
        },
        {
          "title": "我操作的少女正在成为旧日之主",
          "growth": "+4.0万"
        }
      ],
      "summary": "**🔥 题材趋势** 巨兽、克苏鲁、国运、御兽等多元宇宙观与“高武”深度融合。系统、游戏化设定普及，但“嘉豪”、“二阶段”等创意金手指成为新亮点，推动题材创新。\n**📖 读者偏好** 读者对“无敌流”和“爽文”的追求极致，偏好开局即强大、碾压一切的主角。同时，作品设定需有记忆点，如“劲大”、“舞剑开天门”，并追求“人前显圣”的集体情绪价值。\n**🆕 新上榜作品** 《国运求生：我一只鬼被选进去了！》以“鬼”为主角，提供独特求生视角；《我瞎编的禁忌序列，国家当真了》融合“迪化”与“编造”元素，创意十足，具备爆款潜质。\n**📉 掉出榜单** 《穿越异世界：我成为了超人》与《一群机制怪里，出了个劲大的》掉出榜单，提示纯粹的“超人设定”和单一“劲大”卖点的作品竞争激烈，需更强的差异化包装。\n**💡 值得关注** 《濒死触发二阶段？我先捅自己一刀》排名持续上升，其“主动触发变身”的疯批人设和独特战斗机制，提供了可复用的高武新爽点公式。"
    },
    "历史古代": {
      "new_count": 4,
      "dropped_count": 4,
      "new_books": [
        "大明国舅：开局救下常遇春",
        "红楼：开局上京承袭一等侯",
        "让你辅佐曹操，你天天骂他送死",
        "父皇，你要的至尊版太子到了！"
      ],
      "dropped_books": [
        {
          "title": "大唐：妹妹别动手，你先听我说",
          "intro": "985 高材生社畜熬夜猝死，一朝穿越盛唐，竟成唐太宗李世民的养子！ 身负天生盖世神力，文能玩转现代数理化工，武可徒手镇服四方强敌。 上助太宗稳固江山，下以超前知识革新民生。 改良农具兴农耕，普及学识启"
        },
        {
          "title": "朕都摆烂了大乾咋无敌了？",
          "intro": "（评分刚出，后面会涨，新书前期都压分）理工男李轩逸撞大运穿越到了一个陌生朝代，成了皇帝的亲弟弟，本想摆烂躺平，结果没过多久自己那个短命哥哥撒手人寰，自己成了皇帝。 但问题是自己也不懂什么治国理政也没读"
        },
        {
          "title": "战国第八雄：从桀宋到劲宋",
          "intro": "一觉醒来，社畜戴胜成了战国头号背锅侠——宋康王戴偃。 史书上，他是“桀宋”暴君，射天鞭地，穷兵黩武，最终被齐楚魏三国圈踢，身死国灭。 而此时，他刚发动政变，成为宋国新君，距离亡国还有四十三年。 戴胜捋"
        },
        {
          "title": "三国，我为第十九路诸侯争霸天下",
          "intro": "我叫陈渊，字潜龙。是来自二十一世纪的三无青年。 穿越到这个东汉末年的乱世，靠着自己的前世的见识一步步成为汉中郡的县令。 县令只是我的起点，我的目标是结束东汉末年群雄割据的局面，开创一个新的王朝。"
        }
      ],
      "top_risers": [
        {
          "title": "明末：开局吴三桂部将",
          "change": "+7"
        },
        {
          "title": "闲散五皇子",
          "change": "+3"
        },
        {
          "title": "水浒：高太尉和他的一百零八将们",
          "change": "+2"
        }
      ],
      "top_fallers": [
        {
          "title": "为了读书科举，我被迫吃上了软饭",
          "change": "-7"
        },
        {
          "title": "贞观六岁狂王，带着兕子怼朝堂",
          "change": "-2"
        },
        {
          "title": "魂穿大宋皇叔，我成水浒总瓢把子",
          "change": "-2"
        }
      ],
      "reads_growth": [
        {
          "title": "穿女频科举：我写反诗坑死原男主",
          "growth": "+2.3万"
        },
        {
          "title": "穿越大唐成就摆烂诗仙",
          "growth": "+2.2万"
        },
        {
          "title": "给你尊荣你不要，来世我去娶郡主",
          "growth": "+1.9万"
        }
      ],
      "summary": "**🔥 题材趋势** 历史权谋与颠覆性设定仍是核心，但“重生/穿越+女频元素”（如女追男、火葬场）正在抢占头部。明朝、三国题材占据半壁江山，经典角色（朱元璋、曹操）的“改造”故事热度不减，求爽求变成为主流。\n**📖 读者偏好** 读者偏爱“爽点密集”的开局，如开局写反诗、开局救名将。对“无系统”、“无感情戏”的硬核历史文接受度高，但前提是金手指和爽点要足够明确，满足轻松阅读需求。\n**🆕 新上榜作品** 《大明国舅：开局救下常遇春》与《让你辅佐曹操，你天天骂他送死》均以“毒舌”“吐槽”式人物互动为卖点，强化了轻松调侃的氛围，符合当下读者的减压需求。\n**📉 掉出榜单** 《大唐：妹妹别动手，你先听我说》和《朕都摆烂了大乾咋无敌了？》等作品掉榜，说明“摆烂”“躺平”类设定在历史分类中吸引力下降，读者更青睐主动出击的强主角。\n**💡 值得关注** 《明末：开局吴三桂部将》排名上升最快，体现了在宏大历史背景下，书写小人物在绝望中挣扎的“写实”叙事也有市场；而《红楼：开局上京承袭一等侯》将爽文与名著结合，是拓展新题材方向的尝试。"
    },
    "战神赘婿": {
      "new_count": 2,
      "dropped_count": 2,
      "new_books": [
        "我在特勤处扫了十年地",
        "软饭硬吃：冰山老婆求我花她钱"
      ],
      "dropped_books": [
        {
          "title": "送你去毛熊，你在毛熊授衔军街！",
          "intro": "被爷爷断了生活费扔去毛熊留学，所有人都以为林辰会混个文凭回来啃老。 直到五年后，毛熊访问华夏。 全国直播的镜头里，那个穿着毛熊空军制服的年轻人，肩章上的金星亮得刺眼。 他身后站着的，是闻风丧胆的第17"
        },
        {
          "title": "隐龙赘婿：开局觉醒神医传承",
          "intro": "三年前，家族覆灭，他隐姓埋名，入赘苏家，苟全性命。 三年间，忍辱负重，受尽嘲讽，只为等待复仇之日。 当黑龙戒觉醒，传承加身，潜龙终出渊！ 绝世神医救死扶伤，武道至尊横扫强敌，商业巨鳄垄断都市。 曾经的"
        }
      ],
      "top_risers": [
        {
          "title": "你们选假儿子，断亲后悔干什么",
          "change": "+2"
        },
        {
          "title": "离婚后，我让前妻身败名裂",
          "change": "+2"
        },
        {
          "title": "离婚后，高冷前妻排队求复婚",
          "change": "+1"
        }
      ],
      "top_fallers": [
        {
          "title": "兵痞向东",
          "change": "-2"
        },
        {
          "title": "特种兵：说好废柴，这杀神是谁？",
          "change": "-1"
        },
        {
          "title": "深渊防务：在全球战场当死神",
          "change": "-1"
        }
      ],
      "reads_growth": [
        {
          "title": "你们选假儿子，断亲后悔干什么",
          "growth": "+8000"
        },
        {
          "title": "青囊赘婿",
          "growth": "+5000"
        },
        {
          "title": "离婚后，高冷前妻排队求复婚",
          "growth": "+2000"
        }
      ],
      "summary": "**🔥 题材趋势** 传统“兵王+赘婿”模板虽仍是主流，但读者对“虐主”情节的容忍度显著降低，硬刚、不原谅、追夫火葬场成为标配。同时，题材出现多样化变异，如融入“穿书”、“女频逆袭”、“异能收容”等元素，试图打破套路化。\n**📖 读者偏好** 读者对“打脸”和“逆袭”的爽感要求极高，且追求极致与直接，不接受憋屈情节。开局即离婚、净身出户后立刻逆袭的设定大受欢迎，说明读者更青睐快节奏、高回报的叙事。\n**🆕 新上榜作品** 《我在特勤处扫了十年地》凭借“扫地僧”式的反差设定吸引眼球，属于兵王文的变体。《软饭硬吃：冰山老婆求我花她钱》则以“反套路”的软饭模式提供新鲜感。\n**📉 掉出榜单** 《送你去毛熊，你在毛熊授衔军街！》等作品掉榜，显示纯粹依靠宏大叙事或海外军事背景的设定，若缺乏本土化和强互动的都市逆袭元素，吸引力正逐渐减弱。\n**💡 值得关注** 《你们选假儿子，断亲后悔干什么》排名上升明显，其“真假少爷+断亲”的设定，精准切入家庭关系冲突，呼应了当下读者对原生家庭问题的情绪宣泄需求。同时，可关注“软饭硬吃”与“追妻火葬场”融合的新趋势。"
    },
    "都市种田": {
      "new_count": 2,
      "dropped_count": 2,
      "new_books": [
        "都疼假少爷？真少爷搬空家产下乡",
        "家族签到：我在美利坚当幕后黑手"
      ],
      "dropped_books": [
        {
          "title": "县城：女友出国要我卖房，给脸了",
          "intro": "女友出国留学，要李西海卖房供她。 李西海想也不想的拒绝，惨遭泼水，被骂渣男穷比，不欢而散。 意外发现自己能预知股市走向，李西海带着卖房的钱，果断回到家乡，选择躺平。 …… 重仓猛干，浮盈加仓，频繁交易"
        },
        {
          "title": "年代：从大院顽主登顶四九城",
          "intro": "在大院子弟和胡同顽主眼里，院里的林川就是个只会死读书的老实人、任人揉捏的软柿子。 直到天桥剧场外，大院子弟被几十号胡同混混包围，血战一触即发。 半块红砖干脆利落地拍断了北城王腾的鼻梁。 一记飞踹，直接"
        }
      ],
      "top_risers": [
        {
          "title": "宗族：全族供我读书我带全村暴富",
          "change": "+6"
        },
        {
          "title": "八七赶海，老婆真是港岛大小姐",
          "change": "+3"
        },
        {
          "title": "年代：每天拼命，卷哭全村人",
          "change": "+3"
        }
      ],
      "top_fallers": [
        {
          "title": "开局断亲，带百亿物资娶知青",
          "change": "-2"
        },
        {
          "title": "四零年代：我靠打猎养媳妇嫂子",
          "change": "-1"
        }
      ],
      "reads_growth": [
        {
          "title": "年代：地狱开局，我是资本家少爷",
          "growth": "+2.7万"
        },
        {
          "title": "宗族：全族供我读书我带全村暴富",
          "growth": "+2.6万"
        },
        {
          "title": "悠闲渔夫：开局校花怀孕上门",
          "growth": "+8000"
        }
      ],
      "summary": "**🔥 题材趋势** “年代文”依然是绝对主力，但设定重心从单一的“发家致富”转向“家庭关系”与“家族传承”，如宗族振兴、断亲逆袭等。题材空间也在拓展，出现了“高科技现代种田”（如抖音爆火）和“海外种田”（如美利坚发家）等新方向。\n**📖 读者偏好** 读者对“穿越+金手指”的依赖度较高，系统、空间是标配。同时，读者更偏爱“吃喝玩乐”的日常感和“发家致富”的成就感，偏好温馨爽快、节奏明快的故事，而“单女主”或“纯爱”趋势在榜单中也有所体现。\n**🆕 新上榜作品** 《都疼假少爷？真少爷搬空家产下乡》结合“真假少爷”与“年代下乡”热点，属于热点叠加的产物。《家族签到：我在美利坚当幕后黑手》则开辟了海外工业种田新赛道，提供差异化内容。\n**📉 掉出榜单** 《县城：女友出国要我卖房，给脸了》掉出榜单，表明单纯的“情感纠纷”或“都市狗血”剧情，在没有强大金手指支撑的种田分类里，吸引力相对有限。\n**💡 值得关注** 《宗族：全族供我读书我带全村暴富》排名大幅上升，体现了以宗族、乡情、基建为核心的种田文存在巨大潜力，未来发展值得关注。同时，可留意“韩国财阀”与“美利坚发家”这类异域种田文是否形成新的读者群。"
    },
    "传统玄幻": {
      "new_count": 2,
      "dropped_count": 2,
      "new_books": [
        "赐婚公主？我反手取了书院大师姐",
        "人在女尊，逆师逆徒都馋我身子！"
      ],
      "dropped_books": [
        {
          "title": "请神无用？我秒请三清，你不炸了",
          "intro": "（偏群像，偏轻松，主角无敌。） 王朝衰微，皇权虚悬。 各地节度使拥兵自重，各自为政。 兵戈四起，妖魔趁机蚕食人间。 人间浑浊，僧人不认佛祖，道士不闻三清，百姓不知仙神。 佛陀沉沦，仙神隐迹。 假道士苏"
        },
        {
          "title": "征服清冷仙子后，她竟成了我师尊",
          "intro": "（吞噬+爽文+快节奏+多女主+热血升级+无系统） 少年陆枫身穿玄幻世界！ 本想横扫诸天，镇杀万界！ 没想到，开局就被女魔头抓去当成炉鼎，日夜采补。 只因他身怀纯阳体质！ 可惜当世纯阳一脉被天地压制，修"
        }
      ],
      "top_risers": [
        {
          "title": "变嫁：男主请冷静",
          "change": "+4"
        },
        {
          "title": "大婚之日，我阉了未婚妻的白月光",
          "change": "+2"
        },
        {
          "title": "果位修仙：我百年速通金丹！",
          "change": "+2"
        }
      ],
      "top_fallers": [
        {
          "title": "子夜归，入世后我无敌了",
          "change": "-4"
        },
        {
          "title": "我魔道元婴老祖，开局抢夺金手指",
          "change": "-1"
        },
        {
          "title": "穿书百合文，我只想安稳苟到结局",
          "change": "-1"
        }
      ],
      "reads_growth": [
        {
          "title": "大婚之日，我阉了未婚妻的白月光",
          "growth": "+4.0万"
        },
        {
          "title": "穿书百合文，我只想安稳苟到结局",
          "growth": "+2.0万"
        },
        {
          "title": "玄幻：老祖的机缘",
          "growth": "+1.0万"
        }
      ],
      "summary": "**🔥 题材趋势** “被退婚/打脸”与“魔道/反派”题材持续火热，Top20中前者占4席，后者占3席。“老祖、帝皇、世子”等高身份开局仍是核心套路，百合成为了细分赛道新增长点。\n**📖 读者偏好** 读者对“快节奏爽文”和“反转”需求强烈，开篇即高潮的“阉白月光”、“抢金手指”等内容占据在读高位。“反套路”设定（如反派看不上主角）比“正统升级”更受欢迎。\n**🆕 新上榜作品** 《赐婚公主？我反手取了书院大师姐》《人在女尊，逆师逆徒都馋我身子！》均为“女尊”或“女强男弱”的颠覆性设定，将传统玄幻中的性别权力关系进行了反转，是近期的热点。\n**📉 掉出榜单** 《请神无用？我秒请三清，你不炸了》和《征服清冷仙子后，她竟成了我师尊》。前者偏群像轻松，后者为传统升级，表明纯粹群像或传统慢热升级文在当前榜单竞争中处于劣势。\n**💡 值得关注** “变嫁/变百”题材（如《变嫁：男主请冷静》）排名上升迅速，结合“病娇”、“催眠”等元素，显示出该领域在男性向玄幻中开辟了稳定的细分市场。"
    },
    "历史脑洞": {
      "new_count": 5,
      "dropped_count": 5,
      "new_books": [
        "大秦观影：反贼是千古一帝？",
        "天幕乱侃：古代帝王都懵了",
        "被推上皇位后我摊牌了",
        "大唐：武才人？请陛下称太子侧妃",
        "隋唐：龙象镇山河，爆锤李元霸"
      ],
      "dropped_books": [
        {
          "title": "朕还没动手，董卓就成忠臣了？",
          "intro": "【三国】【幕后】【无敌】【 模拟器】【反套路】【苟道】【双主角】 【幕后主角刘协，武力天花板。 叙事主角董卓，故事展开角色。】 /// 我叫刘协，原本只是跟汉献帝重名，没想到现在真穿越了。 好消息：我"
        },
        {
          "title": "我赵括这一生如履薄冰",
          "intro": "大家好，我就是“纸上谈兵”的祖师爷，你们的family——赵括。 刚穿越过来就是长平之战，秦军已经开始推塔了,白起那个杀神还阴在草丛里准备打我的野，根本打不赢好不好。 家人们，我能不能不去长平？ 爱猜"
        },
        {
          "title": "红楼：庶子改命！开局平推漠北",
          "intro": "穿越红楼世界，成贾府卑微庶子，开局觉醒签到系统，面对抄家危机，他弃文从武，左手背嵬军，右手燕云十八骑，直捣漠北，以无敌之姿震慑朝野，誓要在这乱世中逆天改命，杀出一条通天血路！"
        },
        {
          "title": "天幕：我编的明君，他们当真了",
          "intro": "陈渡，扑街三年、稿费不够交房租的历史作者，意外绑定了【天幕创作系统】。 系统让他向南北朝时期的古人投放“未来预言”。 他决定——先编一个明君。 陈义夫，青州流民，出身寒微，二十二岁泰山聚义，均田免税，"
        },
        {
          "title": "九块九的夜明珠，我买下古代县令",
          "intro": "【物品：高锰钢柴刀】 　　大楚武将：此乃削铁如泥的绝世神兵！ 　　夏天：拼多多19块9包邮。 　　【物品：舒肤佳香皂】 　　大楚贵妇：此乃仙家香夷，五两银子一块我也要抢！ 　　夏天：3块5一块，批发还"
        }
      ],
      "top_risers": [
        {
          "title": "杀出玄武门，从踏平罗马称霸全球",
          "change": "+5"
        },
        {
          "title": "我，废物皇子，开局选择项羽模板",
          "change": "+5"
        },
        {
          "title": "刚登基，系统非说我亡国",
          "change": "+5"
        }
      ],
      "top_fallers": [
        {
          "title": "三国：每杀一将，继承其巅峰武技",
          "change": "-3"
        }
      ],
      "reads_growth": [
        {
          "title": "诸天你这天幕怎么老盯着我啊",
          "growth": "+2.4万"
        },
        {
          "title": "我，废物皇子，开局选择项羽模板",
          "growth": "+1.4万"
        },
        {
          "title": "刚登基，系统非说我亡国",
          "growth": "+1.0万"
        }
      ],
      "summary": "**🔥 题材趋势** “天幕曝光/直播”类题材依然是绝对王者，前三名均为此类，且头部效应极其明显。大量“大明”、“大唐”朝代背景作品扎堆，竞争激烈。\n**📖 读者偏好** 读者偏好“系统+基建/争霸”的复合爽感，对“穿越改变历史”的“强设定”容忍度高。同时，“昏君/暴君”系统文凭借强烈的反差感，在读数据稳定，是区别于传统明君的差异化赛道。\n**🆕 新上榜作品** 《大秦观影：反贼是千古一帝？》《天幕乱侃：古代帝王都懵了》均为“天幕”变体，通过“观影”和“短视频”形式制造跨时空信息差，证明该模式生命力极强，且从单一朝代扩展到多朝代对比。\n**📉 掉出榜单** 《朕还没动手，董卓就成忠臣了？》《我赵括这一生如履薄冰》等三国及具体历史人物改编文掉出榜单，说明在“家国争霸”类大爽文面前，过于聚焦特定历史人物的“反套路”创新，除非创意极为惊人，否则难以持续吸引流量。\n**💡 值得关注** 《杀出玄武门，从踏平罗马称霸全球》将战争扩张与全球地图结合，提供了从“大唐”内部争斗向“全球殖民”的升级路径，是“历史脑洞”向“全球史诗”延展的重要信号。"
    },
    "悬疑脑洞": {
      "new_count": 1,
      "dropped_count": 1,
      "new_books": [
        "盗墓：开局抽中sss级人物卡"
      ],
      "dropped_books": [
        {
          "title": "为防止被盗墓，我的棺材无限升级",
          "intro": "【盗墓+系统+每天记录盗墓贼花式死法】 　　林渊醒来发现自己死了，还被埋在劣质棺材里，成了一具自带【阴宅系统】的僵尸。 　　为了防止自己曝尸荒野，林渊只能疯狂给自己的小破坟加装防盗门。 　　“叮！消耗"
        }
      ],
      "top_risers": [
        {
          "title": "僵约：从复刻盘古血脉开始长生",
          "change": "+5"
        },
        {
          "title": "我瞎编的收容会，被全世界当真了",
          "change": "+3"
        },
        {
          "title": "灵异复苏：开局我驾驭了胆小鬼",
          "change": "+2"
        }
      ],
      "top_fallers": [
        {
          "title": "有趣，让我一初升东曦拯救病娇？",
          "change": "-5"
        },
        {
          "title": "卡牌进化：从小土包到九幽地府！",
          "change": "-3"
        },
        {
          "title": "惊悚游戏：我靠捡垃圾养骷髅",
          "change": "-1"
        }
      ],
      "reads_growth": [
        {
          "title": "全球死考：刚下刑场你让我去考试",
          "growth": "+4.9万"
        },
        {
          "title": "全民学校求生：所有学校沦为地狱",
          "growth": "+2.4万"
        },
        {
          "title": "警告！邪神眷属正在杀入诡异副本",
          "growth": "+1.2万"
        }
      ],
      "summary": "**🔥 题材趋势** “无限流/生存考试”与“诡异系统”是霸榜双雄。其中“全球死考”类开创了高压力、高奖励的“极限智战”新范式。同时，“规则怪谈”和“直播探诡”等细分门类热度不减。\n**📖 读者偏好** 读者对“高智商”和“微恐怖”的结合需求强烈，排斥无脑爽。对“颠覆性设定”如“只能靠捡垃圾”、“精神病修仙”接受度高，且喜欢强代入感的“第一人称”或“直播”视角。\n**🆕 新上榜作品** 《盗墓：开局抽中sss级人物卡》是唯一新上榜作品，依托“盗墓”经典IP与“抽卡”系统，成功卡位了悬疑与爽文的结合点，表明经典IP二次开发仍有潜力。\n**📉 掉出榜单** 《为防止被盗墓，我的棺材无限升级》同为盗墓题材但掉榜，可能因“棺材升级”的脑洞未能建立足够爽感，被更简单直接的“抽卡变强”模式取代。老牌作品掉榜也说明该品类更新迭代极快。\n**💡 值得关注** “设定成真”类和“救赎女诡”类新秀（如《我瞎编的收容会》《我的救赎对象全是女诡？》）排名均有上升，前者将脑洞与官方叙事结合，后者则切入“治愈”与“恐怖”的融合情感带，值得进一步观察。"
    },
    "都市脑洞": {
      "new_count": 0,
      "dropped_count": 0,
      "new_books": [],
      "dropped_books": [],
      "top_risers": [
        {
          "title": "你一个煤老板，谈什么科技兴国？",
          "change": "+3"
        },
        {
          "title": "物业费八千，全网直呼良心商家？",
          "change": "+3"
        },
        {
          "title": "让你捉奸，你把出轨女都拿下了？",
          "change": "+3"
        }
      ],
      "top_fallers": [
        {
          "title": "元力引导术，开局满分高考状元",
          "change": "-8"
        },
        {
          "title": "糟了！我的眼睛进化控制不住了",
          "change": "-4"
        },
        {
          "title": "参加个真人秀，怎么送我万民伞了",
          "change": "-1"
        }
      ],
      "reads_growth": [
        {
          "title": "综艺大导演，从齐聚初代跑男开始",
          "growth": "+6.0万"
        },
        {
          "title": "黄牛中介，没想到你请得动真神啊",
          "growth": "+4.1万"
        },
        {
          "title": "开局四选一，我秒选县城婆罗门",
          "growth": "+4.1万"
        }
      ],
      "summary": "**🔥 题材趋势** 系统、直播与“现实职业+超现实脑洞”的融合仍是主流，如丧尸病毒研发、早餐店系统、物业系统等。科技强国与娱乐圈文热度不减，且多采用“打脸”爽文框架。\n**📖 读者偏好** 偏好具有清晰即刻反馈机制的系统设定，如“加价请人”、“幸福值爆奖励”。对“开局即冲突”的强冲突情节（如未婚妻逼婚、全网通缉）接受度高，期待主角快速获得能力并碾压对手。\n**🆕 新上榜作品** 无\n**📉 掉出榜单** 无\n**💡 值得关注** 《你一个煤老板，谈什么科技兴国？》排名上升显著，表明近期读者对“打脸反派+科技强国”类题材偏爱有加。"
    },
    "玄幻脑洞": {
      "new_count": 2,
      "dropped_count": 2,
      "new_books": [
        "夭寿了，老祖宗又双叒叕去表白了",
        "说好未来属于我，他一直天下无敌"
      ],
      "dropped_books": [
        {
          "title": "开局天启神墟神主，大帝只配看门",
          "intro": "（系统 禁区 家族 无敌 天骄 爽文） 评分刚出，后续还会涨！ 苍元大陆，东域禁区·天启神墟。 这里是被天道封禁千万年的上古禁区，苏家和齐下八族盘踞，底蕴恐怖到窒息 。 大帝不如狗，仙王满地走—— 看"
        },
        {
          "title": "稳健修仙：一把抓住，顷刻分解",
          "intro": "【修仙】+【分解】+【爽文】+【长生】+【苟道】+【老六】+【全能】+【种田】+【无女主/单女主】 方远一醒转，就发现自己来到了修仙界。 还好他激发了分解天赋。 可分解万物，获得诸多材料，开局便分解出"
        }
      ],
      "top_risers": [
        {
          "title": "封神：取代李靖，成为哪吒之父！",
          "change": "+1"
        },
        {
          "title": "谁把我仙侠游戏退出键扣了？",
          "change": "+1"
        },
        {
          "title": "别人苦修，你一元买一年修为？！",
          "change": "+1"
        }
      ],
      "top_fallers": [
        {
          "title": "身为万人迷大师兄的我只想下班",
          "change": "-4"
        },
        {
          "title": "喂丹返修为，开局暴击叛逆女修",
          "change": "-2"
        },
        {
          "title": "开挂？谁开的过你们啊！",
          "change": "-2"
        }
      ],
      "reads_growth": [
        {
          "title": "冷宫签到二十年，我举世无敌！",
          "growth": "+3.6万"
        },
        {
          "title": "每秒万年修为，阁下如何应对",
          "growth": "+3.2万"
        },
        {
          "title": "开局仙界帝君，谁还谈恋爱啊！",
          "growth": "+2.9万"
        }
      ],
      "summary": "**🔥 题材趋势** “无敌流”与“反套路”是核心。主角开局即巅峰（帝君、准帝），系统起辅助或制造反差作用。轻松搞笑、系统签到、修为氪金类题材集中涌现。\n**📖 读者偏好** 追求“爽感”和“松弛感”，偏好无需苦修、实力碾压的设定。“苟道”与“无敌”的结合（如签到、氪金）人气高。对家族、血脉、转世等元素有稳定需求。\n**🆕 新上榜作品** 《夭寿了，老祖宗又双叒叕去表白了》、《说好未来属于我，他一直天下无敌》。两者均为轻松无厘头或主角持续碾压的无女主/少女主爽文，延续了当前热度。\n**📉 掉出榜单** 《开局天启神墟神主，大帝只配看门》、《稳健修仙：一把抓住，顷刻分解》。这两本在设定上创新不足，在新书激烈竞争中被挤出。\n**💡 值得关注** 《封神：取代李靖，成为哪吒之父！》排名稳中有升，显示“封神/洪荒”等经典题材的改编与衍生，在结合系统、多女主等元素后，仍具市场潜力。"
    },
    "悬疑灵异": {
      "new_count": 2,
      "dropped_count": 2,
      "new_books": [
        "一觉醒来，我成了杀手47",
        "鬼敲门"
      ],
      "dropped_books": [
        {
          "title": "这个天师有点猛",
          "intro": "四阳之身，阴脉夺魂，法剑在身，遁走阴阳。斩妖魔，破邪煞，斗恶鬼，灭巫蛊…… 我叫上官天洛，叫我一声道爷！"
        },
        {
          "title": "盗墓：都跟你说了是搬山道人",
          "intro": "【真有仪玄】 作为搬山道人有搬山之能很合理吧？ 既然都叫道人了会点道法也正常吧？ “正常.....”吴邪看着单手托举起瓶山的尸体嘴角一抽... 【简介无力，移步正文】"
        }
      ],
      "top_risers": [
        {
          "title": "茅山天师的现代生活",
          "change": "+3"
        },
        {
          "title": "活了一千年，鬼怕我，我怕麻烦",
          "change": "+3"
        },
        {
          "title": "盗墓笔记：秦始皇陵",
          "change": "+2"
        }
      ],
      "top_fallers": [
        {
          "title": "刚分手，我入职省重案组",
          "change": "-3"
        },
        {
          "title": "我在唐山当出马仙",
          "change": "-3"
        },
        {
          "title": "摸鱼当片警，我破了十年灭门惨案",
          "change": "-1"
        }
      ],
      "reads_growth": [
        {
          "title": "茅山天师的现代生活",
          "growth": "+1.1万"
        },
        {
          "title": "活了一千年，鬼怕我，我怕麻烦",
          "growth": "+7000"
        },
        {
          "title": "惊天大案",
          "growth": "+6000"
        }
      ],
      "summary": "**🔥 题材趋势** 港风探案、都市灵异与真实案件改编占据主导。僵尸、风水、出马仙等传统元素结合现代背景（如网约车、片警）是主要创作方向。慢热、无CP的“种田”型灵异文开始出现。\n**📖 读者偏好** 读者偏好强职业设定（警察、天师、出马仙）和清晰世界观。对“港风”氛围、“九叔”类经典IP改编接受度高。偏好带有轻松、搞笑或“咸鱼”人设的解压型灵异故事。\n**🆕 新上榜作品** 《一觉醒来，我成了杀手47》、《鬼敲门》。前者是游戏改编的特工文，后者是典型民俗恐怖，说明小众但硬核的类型仍有受众。\n**📉 掉出榜单** 《这个天师有点猛》、《盗墓：都跟你说了是搬山道人》。两本作品在设定上与其他上榜书同质化较高，且创新点不够突出。\n**💡 值得关注** 《活了一千年，鬼怕我，我怕麻烦》排名上升，其“长生种+反套路”的设定（鬼怕主角，主角怕麻烦）非常讨喜，证明了在悬疑灵异中引入强趣味性设定的成功。"
    },
    "抗战谍战": {
      "new_count": 1,
      "dropped_count": 1,
      "new_books": [
        "抗战：从沪上战役开始"
      ],
      "dropped_books": [
        {
          "title": "抗战：执掌四省，我选择抵抗！",
          "intro": "穿越抗战年代，开局成为副帅！ 四省陷入动荡，大帅却迟迟不做抵抗。 看着数万将士面对百名日军入侵迟迟未动，王战怒了！ 你不打，那我打！ 这大帅你做不了，那老子就替你做！"
        }
      ],
      "top_risers": [
        {
          "title": "多子多福：从皇姑屯拯救大帅开始",
          "change": "+5"
        },
        {
          "title": "抗美援朝之狙神",
          "change": "+3"
        },
        {
          "title": "抗战：我真有一个师去打太原",
          "change": "+1"
        }
      ],
      "top_fallers": [
        {
          "title": "手握原始股，一路打到抗美援朝！",
          "change": "-4"
        },
        {
          "title": "抗日先遣：我率红七军团兵临南京",
          "change": "-2"
        },
        {
          "title": "穿到1940：给延安送百万子弹",
          "change": "-2"
        }
      ],
      "reads_growth": [
        {
          "title": "军阀：大帅义子，前方到站皇姑屯",
          "growth": "+5.3万"
        },
        {
          "title": "军阀：消费返现爆装？成超级列强",
          "growth": "+2.6万"
        },
        {
          "title": "抗战：我真有一个师去打太原",
          "growth": "+1.9万"
        }
      ],
      "summary": "**🔥 题材趋势** 榜单以“军阀/民国+系统/爽文”为核心，架空、轻松向的“海外建国”与“军阀争霸”占比极高；传统严肃谍战仅《潜伏佛龛归来》等少数作品，题材全面向“泛民国爽文”偏移。\n**📖 读者偏好** 读者极度青睐“杀伐果断”的爽文体验，对“多子多福”、“消费返现”等融合系统玩法接受度高；以抗日为背景但淡化苦情色彩，更追求“反杀”、“当严父”的快感。\n**🆕 新上榜作品** 《抗战：从沪上战役开始》融合“系统抽卡+爆兵流”，以正面硬刚的爽感切入，延续了榜单的“金手指爽文”套路。\n**📉 掉出榜单** 《抗战：执掌四省，我选择抵抗！》掉榜，核心原因在于“选择抵抗”的被动定位与当下读者追捧的“主动出击、海外建国”的叙事主流不符。\n**💡 值得关注** 《多子多福：从皇姑屯拯救大帅开始》凭借“时间重置+多子系统”的创意，排名飙升最快，表明“逆天改命+家族经营”是潜力股。"
    },
    "游戏体育": {
      "new_count": 2,
      "dropped_count": 2,
      "new_books": [
        "开局一百创世点，天赋面板自己捏",
        "开局德罗巴模板，教练是穆里尼奥"
      ],
      "dropped_books": [
        {
          "title": "三角洲：什么魔王护，我天榜猎杀",
          "intro": "身为APEX天榜猎杀的苏木，竟然重生到了平行世界。 从此，三角洲的护航界迎来了真正的魔王。 PeRo赏金赛，他以两把31杀的战绩崭露锋芒。 陈泽杯决赛，他以傲人的战绩碾压BBFPS、钢牙、天霸像素等一"
        },
        {
          "title": "CS：老登逆袭，你成职业通天代",
          "intro": "（主队猎鹰+34岁老登指挥+爽文+有老婆不喜误入！） 没人会在意一个半身入土，年过三旬电竞老登，但如果他同时拥有大森残躯+洞主残躯+无背车主+尼の鹰+恐怖乱摸人+22巅峰白毛尼公子+极致前压艺术哥+疯"
        }
      ],
      "top_risers": [
        {
          "title": "NBA：詹皇甩锅，我带队逆转！",
          "change": "+3"
        },
        {
          "title": "DNF开局获得13增幅券",
          "change": "+3"
        },
        {
          "title": "全民神域！我无限背包，横推万界",
          "change": "+2"
        }
      ],
      "top_fallers": [
        {
          "title": "全民木筏求生，开局匹配校花宿舍",
          "change": "-3"
        },
        {
          "title": "三角洲：开局被哈吉瑶捡回棠舟",
          "change": "-2"
        },
        {
          "title": "足球：断球就变强，我成后防真爹",
          "change": "-1"
        }
      ],
      "reads_growth": [
        {
          "title": "木屋求生：我出生在刷怪笼旁",
          "growth": "+2.0万"
        },
        {
          "title": "全民神域！我无限背包，横推万界",
          "growth": "+1.8万"
        },
        {
          "title": "三角洲：FPS暴君降临",
          "growth": "+1.2万"
        }
      ],
      "summary": "**🔥 题材趋势** “三角洲行动”成为游戏类绝对爆款，FPS题材形成集群效应；体育类以NBA和足球为主，重生、系统仍是主流金手指。\n**📖 读者偏好** 极致的“无敌”和“爽感”是核心诉求，《全民神域》中“无限背包”这种无脑横推的设定最受欢迎；体育类读者更爱“打脸”和“复仇叙事”。\n**🆕 新上榜作品** 《开局一百创世点，天赋面板自己捏》凭借“天赋自由定制”的元游戏设定，为同质化的全民求生注入新意；《开局德罗巴模板，教练是穆里尼奥》则瞄准情怀向的“穆式足球”粉丝。\n**📉 掉出榜单** 《三角洲：什么魔王护，我天榜猎杀》掉榜，或因题材与《三角洲》系列高度重叠，在头部作品虹吸效应下难以突破。\n**💡 值得关注** 《NBA：詹皇甩锅，我带队逆转！》排名上升迅速，其“针对球星”的争议性噱头和“系统爽文”模式，精准击中了篮球文的“黑粉”与“逆袭”爽点。"
    },
    "动漫衍生": {
      "new_count": 3,
      "dropped_count": 3,
      "new_books": [
        "人在群聊：我真的不是神",
        "萌学园：满级悟性我真不是炎之星",
        "穿越崩铁：我没有下载美化包"
      ],
      "dropped_books": [
        {
          "title": "战锤40k：金人苏醒",
          "intro": "[评分刚出，后面会涨] 坏消息：卡迪亚陨落，大裂隙撕裂银河，人类帝国危在旦夕！ 好消息：失踪万载的黄金时代的金人，苏醒了！ 开局便是阿巴顿的第十三次黑色远征，卡迪亚被围困，却不知真正的变数在泰拉！ 他"
        },
        {
          "title": "一人：逆生不通天出关吓呆异人界",
          "intro": "【一人之下，无敌，民俗，无女主，民国抗战，弥补遗憾，求仙问道，陆地神仙，岁数极小但辈分极大，内含大量道家典故】 病入膏肓的顾清玄意外穿越异人的世界，成为了三一门左若童的师叔 他悟性逆天，三岁领悟入门，"
        },
        {
          "title": "火影：抽卡变强？开局金色传说",
          "intro": "【非虐主】【爽】【宇智波】【多元化】【非纯火影】【无限流】【目前无女主】 当前【火影】→【星穹铁道】 转生来到忍界降生在宇智波一族的宇智波玄，在年少之时觉醒前世记忆，并进入到了一个满是各种卡牌的迷雾空"
        }
      ],
      "top_risers": [
        {
          "title": "什么贝利亚？叫我光之国二把手！",
          "change": "+8"
        },
        {
          "title": "崩铁：我要验牌，牌没问题",
          "change": "+4"
        },
        {
          "title": "崩铁：深渊水温怎么又高了？",
          "change": "+3"
        }
      ],
      "top_fallers": [
        {
          "title": "聊天群来晚，我已经受赐癫火",
          "change": "-3"
        },
        {
          "title": "黑袍：开局注射v1，抢走祖国人",
          "change": "-3"
        },
        {
          "title": "崩铁：狼尊绝不低头，除非是她爹",
          "change": "-1"
        }
      ],
      "reads_growth": [
        {
          "title": "火影：吾妹美琴，宇智波暴君！",
          "growth": "+2.6万"
        },
        {
          "title": "什么贝利亚？叫我光之国二把手！",
          "growth": "+2.1万"
        },
        {
          "title": "火影：九尾之夜，雷光万劫",
          "growth": "+1.8万"
        }
      ],
      "summary": "**🔥 题材趋势** 火影、奥特曼、崩铁三大IP前三地位稳固，“反套路”和“玩梗”成为主流趋势，如《让蛇叔当火影》的日常解构、《扎基：坏了，这人把我当诺亚练》的错位喜剧。\n**📖 读者偏好** 读者追求“骚操作”和“战力碾压”的极致爽感，对“系统”依赖度降低，更青睐“真·无敌”或“认知错位”带来的戏剧冲突；黑袍纠察队IP热度持续上涨。\n**🆕 新上榜作品** 《穿越崩铁：我没有下载美化包》以“剔除滤镜、直面残酷世界”为卖点，用黑深残视角解构二游世界观，题材新颖；《萌学园：满级悟性》则深耕小众经典IP，表现亮眼。\n**📉 掉出榜单** 《一人：逆生不通天出关吓呆异人界》掉榜，或因传统“练功出关”的套路，在“剧透/社交”等新玩法面前略显平淡。\n**💡 值得关注** 《什么贝利亚？叫我光之国二把手！》排名飙升，其将反派“洗白”并辅以“系统”和“合作发展”的创意，在奥特曼宇宙中提供了新鲜的代入感。"
    },
    "男频衍生": {
      "new_count": 4,
      "dropped_count": 4,
      "new_books": [
        "四合院：开局举报轧钢厂",
        "综武：开局李寻欢，先娶林诗音！",
        "四合院我带三百族人闯入南锣鼓巷",
        "四合院开局我把贾张氏卖给王屠夫"
      ],
      "dropped_books": [
        {
          "title": "四合院：重生后我能天天开盲盒",
          "intro": "主角：赵雷； 角色：无工作的街溜子、赵家边缘人物、爹不亲娘不爱 金手指：盲盒系统 目标：每天躺平，有吃有喝，不用上班 简介：前世身为留守儿童长大的赵雷，在酒店宾馆意外重生在了1959年，此时正是自然灾"
        },
        {
          "title": "影视世界从成为苏明哲开始",
          "intro": "主角穿越成《都挺好》苏明哲《欢乐颂》白主管《三十而已》许幻山《流金岁月》章安仁《人世间》周秉义《知否知否》梁晗等等角色"
        },
        {
          "title": "穿越黑袍，祖国人成了我兄弟！",
          "intro": "【无金手指】【智谋流】【非爽文】 主角穿越到了黑袍纠察队的世界，并且是在第一季第四集即将失事的飞机上，知道剧情的他想要阻止即将发生的悲剧，却好巧不巧撞见了祖国人破坏飞机导航台，导致飞机失事的一幕！ 主"
        },
        {
          "title": "天天挨打？我刘光天跑路香江",
          "intro": "无系统，无系统。 评分刚出，后面会涨。 “儿子，给爹一个机会。”刘海中说道。 “给你机会，当初你又何曾给过我们机会” 穿越成为天天挨打的刘光天，他反手跑路香江。 凭借未来的走向和过人的胆识，刘光天在商"
        }
      ],
      "top_risers": [
        {
          "title": "穿越五一，从喂饱大娄子开始",
          "change": "+6"
        },
        {
          "title": "黑袍：我这真是一家普通安保公司",
          "change": "+3"
        },
        {
          "title": "年代四合院，开局六个装备栏！",
          "change": "+3"
        }
      ],
      "top_fallers": [
        {
          "title": "一人：借术还魂，开局召唤武侯！",
          "change": "-6"
        },
        {
          "title": "名义：空降汉东，瑞金你急什么？",
          "change": "-3"
        },
        {
          "title": "雪中：扫地僧，一掌一个陆地神仙",
          "change": "-1"
        }
      ],
      "reads_growth": [
        {
          "title": "穿越黑袍，开局成为士兵男孩",
          "growth": "+4.3万"
        },
        {
          "title": "一人：沉睡百年，开局抛钱请无常",
          "growth": "+2.9万"
        },
        {
          "title": "黑袍：我这真是一家普通安保公司",
          "growth": "+2.7万"
        }
      ],
      "summary": "**🔥 题材趋势**  \n黑袍纠察队与四合院两大阵营持续霸榜，前者聚焦“教育祖国人/战力碾压”，后者主打“重生复仇打脸”，系统/面板类金手指成为标配。  \n**📖 读者偏好**  \n极致爽文统治榜单，偏好“从开局就碾压原角色”的强力金手指，强调“打脸”“整顿”“教育”的快感。  \n**🆕 新上榜作品**  \n《四合院：开局举报轧钢厂》《四合院我带三百族人闯入南锣鼓巷》《四合院开局我把贾张氏卖给王屠夫》均以“硬刚禽兽邻居+道德绑架”为卖点，批量复制复仇模板；《综武：开局李寻欢，先娶林诗音！》借经典IP走情强+系统路线。  \n**📉 掉出榜单**  \n《四合院：重生后我能天天开盲盒》《影视世界从成为苏明哲"
    }
  }
}